sfzen/__init__.py
sfzen/drumkits.py
sfzen/opcodes.py
sfzen/resampler.py
sfzen/sfz_elems.py
sfzen/sort.py
sfzen/syntax.py
sfzen/cleaners/__init__.py
sfzen/cleaners/liquidsfz.py
sfzen/res/sfz.lark
sfzen/res/syntax.yml
sfzen/scripts/sfz_copy.py
sfzen/scripts/sfz_encoding_check.py
sfzen/scripts/sfz_liquid_safe.py
sfzen/scripts/sfz_opcode_usage.py
sfzen/scripts/sfz_resample.py
sfzen/scripts/sfz_samples.py
sfzen/utils/compile_syntax.py
sfzen/utils/sample_unit_opcodes.py
sfzen-1.8.1.dist-info/entry_points.txt
sfzen-1.8.1.dist-info/LICENSE
sfzen-1.8.1.dist-info/WHEEL
sfzen-1.8.1.dist-info/METADATA
sfzen-1.8.1.dist-info/RECORD
