Metadata-Version: 2.1
Name: sfzen
Version: 1.8.1
Summary: Simple object-oriented SFZ parsing and manipulation.
Author-email: Leon Dionne <ldionne@dridesign.sh.cn>
Classifier: License :: OSI Approved :: GNU General Public License v3 or later (GPLv3+)
Classifier: Programming Language :: Python
Classifier: Programming Language :: Python :: 3.10
Classifier: Topic :: Multimedia :: Sound/Audio :: Sound Synthesis
Classifier: Topic :: Multimedia :: Sound/Audio :: MIDI
Requires-Dist: lark
Requires-Dist: appdirs
Requires-Dist: midi_notes
Requires-Dist: log_soso
Requires-Dist: sox ; extra == "resample"
Project-URL: Home, https://github.com/Zen-Master-SoSo/sfzen
Provides-Extra: resample
